README.rst
setup.cfg
setup.py
pyngboard/__init__.py
pyngboard/client.py
pyngboard/credentials.py
pyngboard.egg-info/PKG-INFO
pyngboard.egg-info/SOURCES.txt
pyngboard.egg-info/dependency_links.txt
pyngboard.egg-info/not-zip-safe
pyngboard.egg-info/requires.txt
pyngboard.egg-info/top_level.txt