Metadata-Version: 1.1
Name: pyngboard
Version: 0.0.5
Summary: A Pingboard Python library
Home-page: https://github.com/tsouza/pyngboard
Author: Thiago Souza
Author-email: thiago@elastic.co
License: MIT
Keywords: pingboard,Pingboard
Platform: UNKNOWN
Classifier: Development Status :: 2 - Pre-Alpha
Classifier: Intended Audience :: Developers
Classifier: Natural Language :: English
Classifier: License :: OSI Approved :: MIT License
Classifier: Programming Language :: Python
Classifier: Programming Language :: Python :: 2.7
